{
    "compiled_at": "2026-07-07T20:38:00+00:00",
    "compiler": "Repository Compiler (PHP)",
    "compiler_version": "1.1.0-mission-009",
    "current_mission": null,
    "next_mission": {
        "id": "010",
        "title": "V2 Foundation & Sequencing Reconciliation",
        "source": "tasks/Backlog.md"
    },
    "completed_mission_count": 8,
    "paused_missions": [
        {
            "id": "006",
            "title": "Validate the Recommendation",
            "status": "Paused — Phase B (operator validation)",
            "reason": "Phase B — operator-executed validation (interviews and smoke test)"
        }
    ],
    "active_strategy": "AI-DOS is a Git-native operating system for AI-assisted software development.",
    "canonical_branch": "main",
    "governance_model": "Merge-to-main is durable approval; chat approval is advisory only (Standards §2).",
    "source_of_truth_statement": "Repository artifacts are canonical. Compiler outputs under site/ are generated views and must not invent facts.",
    "mission_007_v2_architecture": {
        "status": "approved",
        "title": "Design AI-DOS V2"
    },
    "strategic_pivot": "AI-DOS itself is the primary product. Portfolio Projects use a product-agnostic workflow; Mission 006 validates the first candidate (P001).",
    "repository_compiler_concept": "The repository is the source code of the organization. The Repository Compiler (PHP) transforms that source into human-readable Mission Control interfaces.",
    "file_index": {
        "source": "system/file-index.yaml",
        "parse_status": "ok",
        "version": 1,
        "deployment_root": "https://cubixmeow.com/ai-dos/",
        "last_updated": "2026-07-07",
        "entry_count": 47,
        "entries": [
            {
                "path": "README.md",
                "type": "readme",
                "status": "active",
                "public_url": null,
                "safe_to_edit": true,
                "source_or_generated": "source"
            },
            {
                "path": "company/Identity.md",
                "type": "company",
                "status": "active",
                "public_url": null,
                "safe_to_edit": true,
                "source_or_generated": "source"
            },
            {
                "path": "company/Principles.md",
                "type": "company",
                "status": "active",
                "public_url": null,
                "safe_to_edit": true,
                "source_or_generated": "source"
            },
            {
                "path": "company/Standards.md",
                "type": "company",
                "status": "active",
                "public_url": null,
                "safe_to_edit": true,
                "source_or_generated": "source"
            },
            {
                "path": "tasks/Backlog.md",
                "type": "tasks",
                "status": "active",
                "public_url": null,
                "safe_to_edit": true,
                "source_or_generated": "source"
            },
            {
                "path": "workflow/Templates/MissionTemplate.md",
                "type": "template",
                "status": "active",
                "public_url": null,
                "safe_to_edit": true,
                "source_or_generated": "source"
            },
            {
                "path": "system/file-index.yaml",
                "type": "system",
                "status": "active",
                "public_url": null,
                "safe_to_edit": true,
                "source_or_generated": "source"
            },
            {
                "path": "system/file-index.md",
                "type": "system",
                "status": "active",
                "public_url": null,
                "safe_to_edit": true,
                "source_or_generated": "source"
            },
            {
                "path": "compiler/compile.php",
                "type": "compiler",
                "status": "active",
                "public_url": "https://cubixmeow.com/ai-dos/compiler/compile.php",
                "safe_to_edit": true,
                "source_or_generated": "source"
            },
            {
                "path": "compiler/README.md",
                "type": "compiler",
                "status": "active",
                "public_url": null,
                "safe_to_edit": true,
                "source_or_generated": "source"
            },
            {
                "path": "site/index.html",
                "type": "site",
                "status": "active",
                "public_url": "https://cubixmeow.com/ai-dos/site/",
                "safe_to_edit": false,
                "source_or_generated": "generated"
            },
            {
                "path": "site/styles.css",
                "type": "site",
                "status": "active",
                "public_url": "https://cubixmeow.com/ai-dos/site/styles.css",
                "safe_to_edit": false,
                "source_or_generated": "generated"
            },
            {
                "path": "site/data/missions.json",
                "type": "site-data",
                "status": "active",
                "public_url": "https://cubixmeow.com/ai-dos/site/data/missions.json",
                "safe_to_edit": false,
                "source_or_generated": "generated"
            },
            {
                "path": "site/data/organization.json",
                "type": "site-data",
                "status": "active",
                "public_url": "https://cubixmeow.com/ai-dos/site/data/organization.json",
                "safe_to_edit": false,
                "source_or_generated": "generated"
            },
            {
                "path": "site/validation/invoice-tool.html",
                "type": "validation",
                "status": "active",
                "public_url": "https://cubixmeow.com/ai-dos/site/validation/invoice-tool.html",
                "safe_to_edit": true,
                "source_or_generated": "source"
            },
            {
                "path": ".github/workflows/compile-site.yml",
                "type": "workflow",
                "status": "active",
                "public_url": null,
                "safe_to_edit": true,
                "source_or_generated": "source"
            },
            {
                "path": "missions/001-bootstrap/",
                "type": "mission",
                "status": "complete",
                "public_url": null,
                "safe_to_edit": true,
                "source_or_generated": "source"
            },
            {
                "path": "missions/001-bootstrap/mission.md",
                "type": "mission-artifact",
                "status": "complete",
                "public_url": null,
                "safe_to_edit": true,
                "source_or_generated": "source"
            },
            {
                "path": "missions/001-bootstrap/report.md",
                "type": "mission-artifact",
                "status": "complete",
                "public_url": null,
                "safe_to_edit": true,
                "source_or_generated": "source"
            },
            {
                "path": "missions/002-knowledge-preservation/",
                "type": "mission",
                "status": "complete",
                "public_url": null,
                "safe_to_edit": true,
                "source_or_generated": "source"
            },
            {
                "path": "missions/002-knowledge-preservation/mission.md",
                "type": "mission-artifact",
                "status": "complete",
                "public_url": null,
                "safe_to_edit": true,
                "source_or_generated": "source"
            },
            {
                "path": "missions/002-knowledge-preservation/report.md",
                "type": "mission-artifact",
                "status": "complete",
                "public_url": null,
                "safe_to_edit": true,
                "source_or_generated": "source"
            },
            {
                "path": "missions/003-prove-the-loop/",
                "type": "mission",
                "status": "complete",
                "public_url": null,
                "safe_to_edit": true,
                "source_or_generated": "source"
            },
            {
                "path": "missions/003-prove-the-loop/mission.md",
                "type": "mission-artifact",
                "status": "complete",
                "public_url": null,
                "safe_to_edit": true,
                "source_or_generated": "source"
            },
            {
                "path": "missions/003-prove-the-loop/report.md",
                "type": "mission-artifact",
                "status": "complete",
                "public_url": null,
                "safe_to_edit": true,
                "source_or_generated": "source"
            },
            {
                "path": "missions/003-prove-the-loop/research.md",
                "type": "mission-artifact",
                "status": "complete",
                "public_url": null,
                "safe_to_edit": true,
                "source_or_generated": "source"
            },
            {
                "path": "missions/003-prove-the-loop/evaluation.md",
                "type": "mission-artifact",
                "status": "complete",
                "public_url": null,
                "safe_to_edit": true,
                "source_or_generated": "source"
            },
            {
                "path": "missions/004-close-governance-loop/",
                "type": "mission",
                "status": "complete",
                "public_url": null,
                "safe_to_edit": true,
                "source_or_generated": "source"
            },
            {
                "path": "missions/004-close-governance-loop/mission.md",
                "type": "mission-artifact",
                "status": "complete",
                "public_url": null,
                "safe_to_edit": true,
                "source_or_generated": "source"
            },
            {
                "path": "missions/004-close-governance-loop/report.md",
                "type": "mission-artifact",
                "status": "complete",
                "public_url": null,
                "safe_to_edit": true,
                "source_or_generated": "source"
            },
            {
                "path": "missions/005-showcase-page/",
                "type": "mission",
                "status": "complete",
                "public_url": null,
                "safe_to_edit": true,
                "source_or_generated": "source"
            },
            {
                "path": "missions/005-showcase-page/mission.md",
                "type": "mission-artifact",
                "status": "complete",
                "public_url": null,
                "safe_to_edit": true,
                "source_or_generated": "source"
            },
            {
                "path": "missions/005-showcase-page/report.md",
                "type": "mission-artifact",
                "status": "complete",
                "public_url": null,
                "safe_to_edit": true,
                "source_or_generated": "source"
            },
            {
                "path": "missions/006-validate-recommendation/",
                "type": "mission",
                "status": "paused",
                "public_url": null,
                "safe_to_edit": true,
                "source_or_generated": "source"
            },
            {
                "path": "missions/006-validate-recommendation/mission.md",
                "type": "mission-artifact",
                "status": "paused",
                "public_url": null,
                "safe_to_edit": true,
                "source_or_generated": "source"
            },
            {
                "path": "missions/006-validate-recommendation/phase-a-thresholds.md",
                "type": "mission-artifact",
                "status": "complete",
                "public_url": null,
                "safe_to_edit": true,
                "source_or_generated": "source"
            },
            {
                "path": "missions/006-validate-recommendation/evidence-ledger.md",
                "type": "mission-artifact",
                "status": "active",
                "public_url": null,
                "safe_to_edit": true,
                "source_or_generated": "source"
            },
            {
                "path": "missions/007-design-v2/",
                "type": "mission",
                "status": "complete",
                "public_url": null,
                "safe_to_edit": true,
                "source_or_generated": "source"
            },
            {
                "path": "missions/007-design-v2/mission.md",
                "type": "mission-artifact",
                "status": "complete",
                "public_url": null,
                "safe_to_edit": true,
                "source_or_generated": "source"
            },
            {
                "path": "missions/007-design-v2/report.md",
                "type": "mission-artifact",
                "status": "complete",
                "public_url": null,
                "safe_to_edit": true,
                "source_or_generated": "source"
            },
            {
                "path": "missions/007-design-v2/architecture.md",
                "type": "architecture",
                "status": "active",
                "public_url": null,
                "safe_to_edit": true,
                "source_or_generated": "source"
            },
            {
                "path": "missions/008-repository-compiler/",
                "type": "mission",
                "status": "complete",
                "public_url": null,
                "safe_to_edit": true,
                "source_or_generated": "source"
            },
            {
                "path": "missions/008-repository-compiler/mission.md",
                "type": "mission-artifact",
                "status": "complete",
                "public_url": null,
                "safe_to_edit": true,
                "source_or_generated": "source"
            },
            {
                "path": "missions/008-repository-compiler/report.md",
                "type": "mission-artifact",
                "status": "complete",
                "public_url": null,
                "safe_to_edit": true,
                "source_or_generated": "source"
            },
            {
                "path": "missions/009-file-index-foundation/",
                "type": "mission",
                "status": "in_progress",
                "public_url": null,
                "safe_to_edit": true,
                "source_or_generated": "source"
            },
            {
                "path": "missions/009-file-index-foundation/mission.md",
                "type": "mission-artifact",
                "status": "in_progress",
                "public_url": null,
                "safe_to_edit": true,
                "source_or_generated": "source"
            },
            {
                "path": "missions/009-file-index-foundation/report.md",
                "type": "mission-artifact",
                "status": "in_progress",
                "public_url": null,
                "safe_to_edit": true,
                "source_or_generated": "source"
            }
        ]
    }
}
